{"frames":[{"indices":[],"prefix":"left","offset":{"x":-169,"y":94},"looped":false,"flipX":false,"flipY":false,"name":"SingLEFT","frameRate":24},{"indices":[],"prefix":"down","offset":{"x":21,"y":91},"looped":false,"flipX":false,"flipY":false,"name":"SingDOWN","frameRate":24},{"indices":[],"prefix":"up","offset":{"x":-35,"y":11},"looped":false,"flipX":false,"flipY":false,"name":"SingUP","frameRate":24},{"indices":[],"prefix":"right","offset":{"x":58,"y":107},"looped":false,"flipX":false,"flipY":false,"name":"SingRIGHT","frameRate":24},{"indices":[],"prefix":"idle","offset":{"x":40,"y":90},"looped":true,"flipX":false,"flipY":false,"name":"dance","frameRate":24}],"singDuration":8,"format":"sparrow","png":"assets/images/game/Character/GARRETT","xml":"assets/images/game/Character/GARRETT","danceInterval":2,"flipX":false,"flipY":false,"antialiasing":true,"name":"GARRETT","danceSteps":["dance"],"scale":{"x":1.05,"y":1.05}}